observabilityclient/__init__.py
observabilityclient/client.py
observabilityclient/i18n.py
observabilityclient/plugin.py
observabilityclient/prometheus_client.py
observabilityclient/rbac.py
observabilityclient/tests/functional/__init__.py
observabilityclient/tests/functional/base.py
observabilityclient/tests/functional/test_cli.py
observabilityclient/tests/functional/test_python_api.py
observabilityclient/tests/unit/__init__.py
observabilityclient/tests/unit/test_cli.py
observabilityclient/tests/unit/test_prometheus_client.py
observabilityclient/tests/unit/test_python_api.py
observabilityclient/tests/unit/test_rbac.py
observabilityclient/tests/unit/test_utils.py
observabilityclient/utils/__init__.py
observabilityclient/utils/metric_utils.py
observabilityclient/v1/__init__.py
observabilityclient/v1/base.py
observabilityclient/v1/cli.py
observabilityclient/v1/client.py
observabilityclient/v1/python_api.py
python_observabilityclient-1.2.0.dist-info/AUTHORS
python_observabilityclient-1.2.0.dist-info/LICENSE
python_observabilityclient-1.2.0.dist-info/METADATA
python_observabilityclient-1.2.0.dist-info/WHEEL
python_observabilityclient-1.2.0.dist-info/entry_points.txt
python_observabilityclient-1.2.0.dist-info/pbr.json
python_observabilityclient-1.2.0.dist-info/top_level.txt
python_observabilityclient-1.2.0.dist-info/RECORD
