Metadata-Version: 2.1
Name: python-observabilityclient
Version: 1.2.0
Summary: OpenStack Observability Client
Home-page: https://opendev.org/openstack/python-observabilityclient
Author: OpenStack
Author-email: openstack-discuss@lists.openstack.org
License: Apache License, Version 2.0
Classifier: Environment :: Console
Classifier: Environment :: OpenStack
Classifier: Intended Audience :: Developers
Classifier: Intended Audience :: Information Technology
Classifier: Intended Audience :: System Administrators
Classifier: License :: OSI Approved :: Apache Software License
Classifier: Operating System :: OS Independent
Classifier: Programming Language :: Python
Classifier: Programming Language :: Python :: Implementation :: CPython
Classifier: Programming Language :: Python :: 3 :: Only
Classifier: Programming Language :: Python :: 3
Classifier: Programming Language :: Python :: 3.10
Classifier: Programming Language :: Python :: 3.11
Classifier: Programming Language :: Python :: 3.12
Requires-Python: >=3.10
License-File: LICENSE
License-File: AUTHORS
Requires-Dist: osc-lib >=1.0.1
Requires-Dist: keystoneauth1 >=1.0.0
Requires-Dist: cliff >=1.14.0
Requires-Dist: PyYAML >5.1
